javap -c InnerClassDemo\$C1.class 

Compiled from "InnerClassDemo.java"
class oo.InnerClassDemo$C1 {
  final oo.InnerClassDemo this$0;

  oo.InnerClassDemo$C1(oo.InnerClassDemo);
    Code:
       0: aload_0       
       1: aload_1       
       2: putfield      #10                 // Field this$0:Loo/InnerClassDemo;
       5: aload_0       
       6: invokespecial #12                 // Method java/lang/Object."<init>":()V
       9: return        

  public int sum();
    Code:
       0: aload_0       
       1: getfield      #10                 // Field this$0:Loo/InnerClassDemo;
       4: getfield      #21                 // Field oo/InnerClassDemo.i1:I
       7: aload_0       
       8: getfield      #10                 // Field this$0:Loo/InnerClassDemo;
      11: getfield      #27                 // Field oo/InnerClassDemo.i2:I
      14: iadd          
      15: ireturn       
}
